pwchkr/__init__.py
pwchkr/pwchkr.py
pwchkr-0.1.0.dist-info/METADATA
pwchkr-0.1.0.dist-info/WHEEL
pwchkr-0.1.0.dist-info/top_level.txt
pwchkr-0.1.0.dist-info/RECORD
