Metadata-Version: 2.4
Name: pwchkr
Version: 0.1.0
Summary: Vérification de mot de passe avec score et détection de codes communs, adapté au français.
License: MIT
Requires-Python: >=3.10
